<?xml version="1.0" encoding="utf-8" ?>
<Materials>
  <Material Name="Macbeth Color Checker White Patch (No. 19)">
    <WaveData Start="380" End="780" Step="10">
      0.153 0.245 0.409 0.671 0.84 0.878 0.883 0.886 0.887 0.888 0.888 0.888 0.887 0.887 0.887 0.887 0.887 0.886 0.887 0.888 0.887
      0.886 0.887 0.889 0.891 0.891 0.89 0.889 0.889 0.888 0.888 0.888 0.888 0.886 0.886 0.885 0.884 0.883 0.882 0.88 0.879
    </WaveData>
  </Material>
  <Material Name="Macbeth Color Checker Brown Patch (No. 1)">
    <WaveData Start="380" End="850" Step="10">
      0.048 0.055 0.065 0.068 0.064 0.059 0.055 0.053 0.052 0.052 0.054 0.057 0.061 0.065 0.07 0.074 0.076 0.079
      0.087 0.1 0.115 0.129 0.138 0.146 0.154 0.163 0.173 0.188 0.204 0.222 0.242 0.261 0.282 0.305 0.334 0.372 0.409
      0.436 0.462 0.448 0.421 0.4 0.38 0.36 0.34 0.32 0.3 0.3

    </WaveData>
  </Material>
  <Material Name="Macbeth Color Checker Skin Patch (No. 2)">
    <WaveData Start="380" End="780" Step="10">
      0.103 0.141 0.182 0.197 0.201 0.205 0.212 0.224 0.24 0.262 0.282 0.293 0.301 0.321 0.322 0.298 0.292 0.3 0.295 0.305
      0.358 0.435 0.494 0.53 0.55 0.564 0.574 0.59 0.605 0.624 0.652 0.682 0.713 0.745 0.762 0.783 0.791 0.789 0.801 0.771 0.734
    </WaveData>
  </Material>
  <Material Name="Macbeth Color Checker Sky Blue Patch (No. 3)">
    <WaveData Start="380" End="780" Step="10">
      0.113 0.174 0.266 0.32 0.336 0.337 0.335 0.331 0.322 0.31 0.293 0.276 0.26 0.243 0.225 0.208 0.198 0.191 0.183 0.172
      0.163 0.157 0.15 0.144 0.137 0.13 0.123 0.118 0.112 0.108 0.105 0.104 0.103 0.102 0.102 0.102 0.104 0.104 0.106 0.11 0.12
    </WaveData>
  </Material>
  <Material Name="Macbeth Color Checker Green Patch (No. 4)">
    <WaveData Start="380" End="780" Step="10">
      0.048 0.049 0.05 0.049 0.05 0.052 0.054 0.058 0.061 0.064 0.067 0.07 0.078 0.106 0.155 0.181 0.177 0.157 0.137 0.126 0.122
      0.115 0.104 0.098 0.098 0.1 0.097 0.095 0.095 0.101 0.125 0.174 0.247 0.311 0.343 0.358 0.364 0.362 0.368 0.355 0.341
    </WaveData>
  </Material>
  <Material Name="Macbeth Color Checker Light Purple Patch (No. 5)">
    <WaveData Start="380" End="780" Step="10">
      0.123 0.197 0.328 0.418 0.446 0.448 0.444 0.434 0.421 0.405 0.381 0.362 0.342 0.314 0.271 0.231 0.211 0.209 0.201 0.196
      0.206 0.223 0.235 0.245 0.243 0.247 0.269 0.318 0.384 0.446 0.49 0.511 0.52 0.523 0.521 0.522 0.521 0.514 0.517 0.5 0.487
    </WaveData>
  </Material>
  <Material Name="Macbeth Color Checker Aqua Marine Blue Patch (No. 6)">
    <WaveData Start="380" End="780" Step="10">
      0.11 0.167 0.252 0.303 0.322 0.336 0.353 0.375 0.408 0.46 0.523 0.566 0.582 0.58 0.569 0.549 0.519 0.48 0.436 0.392 0.346 0.302 0.26
      0.234 0.221 0.215 0.21 0.208 0.211 0.22 0.233 0.244 0.252 0.25 0.244 0.245 0.26 0.278 0.297 0.297 0.296
    </WaveData>
  </Material>
  <Material Name="Macbeth Color Checker Orange Patch (No. 7)">
    <WaveData Start="380" End="780" Step="10">
      0.053 0.054 0.054 0.053 0.052 0.052 0.052 0.052 0.052 0.053 0.055 0.057 0.061 0.068 0.086 0.12 0.17 0.228 0.297 0.38 0.452 0.503 0.532
      0.552 0.566 0.578 0.587 0.599 0.604 0.608 0.615 0.622 0.628 0.633 0.633 0.637 0.638 0.633 0.641 0.616 0.582
    </WaveData>
  </Material>
  <Material Name="Macbeth Color Checker Blue Patch (No. 8)">
    <WaveData Start="380" End="780" Step="10">
      0.099 0.15 0.231 0.293 0.324 0.348 0.373 0.387 0.374 0.345 0.301 0.247 0.202 0.167 0.137 0.116 0.106 0.099 0.09 0.083 0.083 0.086
      0.087 0.085 0.084 0.088 0.098 0.111 0.123 0.126 0.12 0.115 0.116 0.12 0.128 0.139 0.162 0.197 0.242 0.275 0.316
    </WaveData>
  </Material>
  <Material Name="Macbeth Color Checker Peach Patch (No. 9)">
    <WaveData Start="380" End="780" Step="10">
      0.096 0.123 0.144 0.144 0.138 0.132 0.131 0.129 0.126 0.125 0.119 0.109 0.103 0.1 0.094 0.089 0.092 0.102 0.108 0.112 0.157 0.274 0.415
      0.517 0.567 0.591 0.601 0.607 0.607 0.605 0.605 0.605 0.606 0.602 0.599 0.596 0.593 0.584 0.586 0.566 0.54
    </WaveData>
  </Material>
  <Material Name="Macbeth Color Checker Purple Patch (No. 10)">
    <WaveData Start="380" End="780" Step="10">
      0.101 0.135 0.177 0.199 0.206 0.19 0.168 0.144 0.12 0.101 0.086 0.075 0.067 0.061 0.058 0.054 0.052 0.053 0.055 0.054 0.052 0.053 0.059
      0.074 0.099 0.126 0.149 0.172 0.193 0.217 0.248 0.282 0.319 0.355 0.388 0.422 0.451 0.471 0.492 0.482 0.467
    </WaveData>
  </Material>
  <Material Name="Macbeth Color Checker Lime Green Patch (No. 11)">
    <WaveData Start="380" End="780" Step="10">
      0.056 0.059 0.06 0.061 0.062 0.064 0.068 0.075 0.085 0.104 0.135 0.185 0.269 0.384 0.484 0.534 0.545 0.533 0.513 0.487 0.454 0.416 0.374
      0.346 0.331 0.325 0.32 0.319 0.324 0.337 0.354 0.368 0.379 0.379 0.373 0.375 0.392 0.412 0.433 0.426 0.404
    </WaveData>
  </Material>
  <Material Name="Macbeth Color Checker Dark Yellow Patch (No. 12)">
    <WaveData Start="380" End="780" Step="10">
      0.06 0.063 0.065 0.064 0.064 0.064 0.065 0.067 0.069 0.077 0.092 0.107 0.123 0.146 0.193 0.273 0.374 0.456 0.512 0.554 0.584 0.609 0.624
      0.635 0.645 0.654 0.662 0.672 0.676 0.678 0.685 0.69 0.696 0.698 0.698 0.701 0.701 0.694 0.7 0.673 0.639
    </WaveData>
  </Material>
  <Material Name="Macbeth Color Checker Royal Blue Patch (No. 13)">
    <WaveData Start="380" End="780" Step="10">
      0.069 0.096 0.136 0.175 0.208 0.244 0.29 0.335 0.338 0.302 0.239 0.172 0.12 0.086 0.066 0.054 0.048 0.045 0.043 0.041 0.04 0.04 0.039
      0.04 0.04 0.041 0.042 0.042 0.043 0.044 0.044 0.045 0.048 0.051 0.056 0.064 0.079 0.104 0.138 0.168 0.204
    </WaveData>
  </Material>
  <Material Name="Macbeth Color Checker Dark Green Patch (No. 14)">
    <WaveData Start="380" End="780" Step="10">
      0.055 0.057 0.058 0.059 0.059 0.062 0.065 0.07 0.078 0.091 0.113 0.14 0.18 0.244 0.324 0.363 0.355 0.323 0.281 0.238 0.196 0.158 0.124
      0.101 0.089 0.084 0.08 0.077 0.075 0.075 0.078 0.082 0.088 0.089 0.09 0.089 0.094 0.102 0.11 0.112 0.112
    </WaveData>
  </Material>
  <Material Name="Macbeth Color Checker Red Patch (No. 15)">
    <WaveData Start="380" End="780" Step="10">
      0.052 0.052 0.051 0.05 0.049 0.049 0.049 0.049 0.048 0.047 0.045 0.044 0.044 0.044 0.044 0.044 0.045 0.047 0.05 0.057 0.072 0.109
      0.192 0.332 0.486 0.598 0.654 0.686 0.7 0.707 0.718 0.724 0.729 0.73 0.727 0.729 0.727 0.721 0.728 0.702 0.664
    </WaveData>
  </Material>
  <Material Name="Macbeth Color Checker Yellow Patch (No. 16)">
    <WaveData Start="380" End="780" Step="10">
      0.054 0.054 0.053 0.053 0.052 0.053 0.053 0.055 0.059 0.075 0.121 0.202 0.303 0.394 0.475 0.544 0.597 0.63 0.66 0.686 0.708 0.726 0.737
      0.746 0.753 0.761 0.768 0.777 0.78 0.781 0.785 0.787 0.792 0.793 0.79 0.792 0.787 0.778 0.782 0.752 0.71
    </WaveData>
  </Material>
  <Material Name="Sky Blue Metamer 3 (Under D65)">
    <WaveData Start="380" End="780" Step="10">
      0.1835929
      0.2238176
      0.584255
      0.05903798
      0.5399517
      0.2624731
      0.3998075
      0.880392
      0.04406843
      0.1717975
      0.07062953
      0.2373397
      0.688
      0.1629624
      0.6595895
      0.2411833
      0.04464712
      0.2923262
      0.1597735
      0.06405038
      0.2836166
      0.07699112
      0.02115251
      0.1185443
      0.3283068
      0.5555597
      0.4636586
      0.3371762
      0.1578754
      0.906927
      0.2579683
      0.5766189
      0.04396035
      0.1098551
      0.1738007
      0.9625474
      0.1873578
      0.3517096
      0.6625218
      0.8549175
      0.8697093
    </WaveData>
  </Material>
  <Material Name="Sky Blue Metamer 4 (Under D65)">
    <WaveData Start="380" End="780" Step="10">
      0.8067072
      0.8522735
      0.3450761
      0.07694522
      0.4371913
      0.1686162
      0.3169848
      0.08610019
      0.9248065
      -0.05379253
      0.2375372
      0.4600101
      0.6748755
      -0.1140059
      0.5860406
      0.1078332
      0.003313784
      -0.08002274
      0.2316929
      0.6514524
      0.1622382
      0.05889714
      0.03893169
      0.3452091
      -0.1355556
      0.4652825
      -0.1623323
      0.1144741
      0.72746
      0.3197078
      0.7982334
      -0.06157613
      0.144996
      -0.02032028
      -0.01749707
      0.2117038
      0.8409944
      0.4020095
      0.8122249
      0.7147254
      0.500869
    </WaveData>
  </Material>
  <Material Name="Sky Blue Metamer 6 (Under D65)">
    <WaveData Start="380" End="780" Step="10">
      0.2283799
      0.250684
      0.1967961
      0.4430227
      0.5314817
      0.9230997
      0.3450336
      0.4749368
      0
      0.227962
      0.01844852
      0.1466171
      0.220563
      0
      0.3865336
      0.4968312
      0.1593716
      0.2153365
      0.1294711
      0
      0.2933913
      0.009926894
      0.4436539
      0
      0
      0.02602335
      0.4690845
      0.5886509
      0
      0.5704907
      0
      0.1910867
      0.09528553
      0.09896185
      0.01422279
      0.2910475
      0
      0.1786142
      0.329666
      0.3514044
      0.9199224
    </WaveData>
  </Material>
  <Material Name="Light Purple Metamer 1 (Under D65)">
    <WaveData Start="380" End="780" Step="10">
      0.5955431
      0.8860139
      0.1920603
      0.4179504
      0.4654739
      0.2987469
      0.6139755
      0.5365502
      0.03578806
      0.1559969
      0.9408832
      0.4178812
      0.2885695
      0.5415196
      0.3382105
      0.0645885
      0.1693611
      0.2744097
      0.1863165
      0.1300844
      0.3135173
      0.1716253
      0.1617897
      0.5567802
      0.01268219
      0.130173
      0.5855475
      0.813262
      0.5884271
      0.3485335
      0.06952044
      0.4859984
      0.6594779
      0.7900059
      0.7342718
      0.5227572
      0.9987506
      0.5835679
      0.8697779
      0.2300432
      0.9580489
    </WaveData>
  </Material>
  <Material Name="Lime Green Metamer 1 (Under SP35)">
    <WaveData Start="380" End="780" Step="10">
      0.3091314
      0.9577031
      0.7282601
      0.5758261
      0.6919945
      0.1280352
      0.1473651
      0.1176619
      0.02502075
      0.001086017
      0.03352168
      0.1642642
      0.6085208
      0.2249202
      0.5604997
      0.9390554
      0.5092086
      0.5305996
      0.87911
      0.2681546
      0.3457466
      0.08336813
      0.3892998
      0.1015968
      0.866837
      0.5229091
      0.1724671
      0.3319657
      0.4451771
      0.7661202
      0.8856467
      0.6172823
      0.9116188
      0.9701736
      0.5562602
      0.2784959
      0.3355015
      0.358891
      0.494677
      0.3493095
      0.7426907
    </WaveData>
  </Material>
</Materials>